rustbinsign/__init__.py
rustbinsign/compilation.py
rustbinsign/exceptions.py
rustbinsign/logger.py
rustbinsign/main.py
rustbinsign/model.py
rustbinsign/rustup.py
rustbinsign/sig_providers/ida/ida.py
rustbinsign/sig_providers/ida/idb2pat.py
rustbinsign/sig_providers/ida/model.py
rustbinsign/sig_providers/provider_base.py
rustbinsign/signature_generation.py
rustbinsign/subcommands/download.py
rustbinsign/subcommands/sign.py
rustbinsign/toolchain.py
rustbinsign/toolchains/__init__.py
rustbinsign/toolchains/default.py
rustbinsign/toolchains/mingw/__init__.py
rustbinsign/toolchains/model.py
rustbinsign/toolchains/musl/__init__.py
rustbinsign/toolchains/musl/transforms/hyper.py
rustbinsign/util.py
rustbinsign-0.1.1.dist-info/LICENSE
rustbinsign-0.1.1.dist-info/METADATA
rustbinsign-0.1.1.dist-info/WHEEL
rustbinsign-0.1.1.dist-info/entry_points.txt
rustbinsign-0.1.1.dist-info/RECORD
