Metadata-Version: 2.1
Name: rustbinsign
Version: 0.1.1
Summary: A tool to help you unstrip rust executables
Author: Nofix
Author-email: 16479266+N0fix@users.noreply.github.com
Requires-Python: >=3.10,<4.0
Classifier: Programming Language :: Python :: 3
Classifier: Programming Language :: Python :: 3.10
Classifier: Programming Language :: Python :: 3.11
Requires-Dist: gitpython (>=3.1.41,<4.0.0)
Requires-Dist: packaging (>=23.2,<24.0)
Requires-Dist: parse (>=1.20.0,<2.0.0)
Requires-Dist: pydantic (>=2.5.2,<3.0.0)
Requires-Dist: requests (>=2.31.0,<3.0.0)
Requires-Dist: rich (>=13.7.0,<14.0.0)
Requires-Dist: rustbininfo (>=0.4.1,<0.5.0)
Requires-Dist: semver (>=3.0.2,<4.0.0)
Requires-Dist: toml (>=0.10.2,<0.11.0)
